bratly/eval/__init__.py
bratly/eval/agreement_types.py
bratly/eval/eval_src/__init__.py
bratly/eval/eval_src/compare_batch.py
bratly/eval/eval_src/count_tokens.py
bratly/eval/py.typed
bratly_eval-0.1.4.dist-info/WHEEL
bratly_eval-0.1.4.dist-info/METADATA
bratly_eval-0.1.4.dist-info/RECORD
